CMash/FunctionOfK.py
CMash/Ideas.py
CMash/KhmerApproachSerial.py
CMash/MinHash.py
CMash/Test.py
CMash/TestArgeparse.py
CMash/__init__.py
CMash/data/PRJNA298068.fna
CMash/data/PRJNA32727.fna
CMash/data/PRJNA67111.fna
CMash-0.3.0.data/scripts/MakeDNADatabase.py
CMash-0.3.0.data/scripts/MakeNodeGraph.py
CMash-0.3.0.data/scripts/MakeStreamingDNADatabase.py
CMash-0.3.0.data/scripts/QueryDNADatabase.py
CMash-0.3.0.data/scripts/StreamingQueryDNADatabase.py
CMash-0.3.0.dist-info/DESCRIPTION.rst
CMash-0.3.0.dist-info/METADATA
CMash-0.3.0.dist-info/RECORD
CMash-0.3.0.dist-info/WHEEL
CMash-0.3.0.dist-info/metadata.json
CMash-0.3.0.dist-info/top_level.txt
