Metadata-Version: 2.0
Name: CMash
Version: 0.3.0
Summary: Fast and accurate set similarity estimation via containment min hash (for genomic datasets).
Home-page: https://github.com/dkoslicki/CMash
Author: David Koslicki
Author-email: dmkoslicki@gmail.com
License: UNKNOWN
Keywords: jaccard min hash containment genomics metagenomics
Platform: UNKNOWN
Classifier: Development Status :: 3 - Alpha
Classifier: Topic :: Scientific/Engineering :: Bio-Informatics
Classifier: Topic :: Scientific/Engineering :: Mathematics
Classifier: Programming Language :: Python :: 2.7
Classifier: License :: OSI Approved :: BSD License
Classifier: Intended Audience :: Science/Research
Classifier: Programming Language :: Python :: 3.5
Classifier: Natural Language :: English
Classifier: Operating System :: MacOS :: MacOS X
Classifier: Operating System :: POSIX :: Linux
Requires-Dist: khmer (>=2.1.1)
Requires-Dist: screed
Requires-Dist: h5py
Requires-Dist: numpy
Requires-Dist: blist
Requires-Dist: argparse
Requires-Dist: pandas
Requires-Dist: setuptools (>=24.2.0)
Requires-Dist: six
Requires-Dist: scipy
Requires-Dist: matplotlib
